pln_fx/__init__.py
pln_fx/fx.py
pln_fx-0.0.9.dist-info/METADATA
pln_fx-0.0.9.dist-info/WHEEL
pln_fx-0.0.9.dist-info/top_level.txt
pln_fx-0.0.9.dist-info/RECORD
