Metadata-Version: 2.1
Name: pln-fx
Version: 0.0.9
Summary: Get rates from the Polish National Bank (Narodowy Bank Polski)
Home-page: https://github.com/stephansemerad/National-Bank-of-Poland-Rates
Author: Stephan Semerad
Author-email: <stephan.semerad@gmail.com>
License: UNKNOWN
Keywords: python,poland,fx,exchange rates,exchange,pln,plnfx,zloty
Platform: UNKNOWN
Classifier: Development Status :: 4 - Beta
Classifier: Intended Audience :: Developers
Classifier: Programming Language :: Python :: 3
Classifier: Operating System :: Unix
Classifier: Operating System :: MacOS :: MacOS X
Classifier: Operating System :: Microsoft :: Windows
Requires-Dist: requests
